[
{
"clue": "Insect of the family Formicidae which lives in colonies",
"answer": "ANT"
},
{
"clue": "A stake put up by players before receiving cards",
"answer": "ANTE"
},
{
"clue": "Obtained money for labour or services",
"answer": "EARNT"
},
{
"clue": "Temporary possession for a fee",
"answer": "RENTAL"
},
{
"clue": "Not supporting or helping opposing sides",
"answer": "NEUTRAL"
},
{
"clue": "Follower of a 16th century branch of Protestantism",
"answer": "LUTHERAN"
},
{
"clue": "Not of this world: unnatural or mysterious",
"answer": "UNEARTHLY"
}
]
