[
{
"clue": "Acronym for Local Area Network",
"answer": "LAN"
},
{
"clue": "Assumed a horizontal position at rest",
"answer": "LAIN"
},
{
"clue": "Classic language of Rome",
"answer": "LATIN"
},
{
"clue": "Involve something as a part of",
"answer": "ENTAIL"
},
{
"clue": "Colorless, flavourless food ingredient derived from collagen",
"answer": "GELATIN"
},
{
"clue": "Necessary to make a whole complete",
"answer": "INTEGRAL"
},
{
"clue": "Moving unsteadily or hesitantly",
"answer": "FALTERING"
},
{
"clue": "Full of praise or compliments",
"answer": "FLATTERING"
}
]
