[
{
"clue": "A loud noise or commotion",
"answer": "DIN"
},
{
"clue": "The tough outer layer of fruit or cheese",
"answer": "RIND"
},
{
"clue": "Currency of several Middle Eastern countries",
"answer": "DINAR"
},
{
"clue": "Make someone a priest or minister",
"answer": "ORDAIN"
},
{
"clue": "A type of barometer using no liquid",
"answer": "ANEROID"
},
{
"clue": "Confident, stylish and charming",
"answer": "DEBONAIR"
},
{
"clue": "Shoulder belt with loops or pockets for cartridges",
"answer": "BANDOLIER"
}
]
