[
{
"clue": "A member of the rodent family",
"answer": "RAT"
},
{
"clue": "A small mountain lake",
"answer": "TARN"
},
{
"clue": "A long piece of material attached to the back of a formal dress or robe",
"answer": "TRAIN"
},
{
"clue": "To make a great effort",
"answer": "STRAIN"
},
{
"clue": "A worker in a skilled trade",
"answer": "ARTISAN"
},
{
"clue": "A person having knowledge of a secret process",
"answer": "ARCANIST"
},
{
"clue": "Waterproof outer layers",
"answer": "RAINCOATS"
},
{
"clue": "A surgical procedure by which a eunuch is produced",
"answer": "CASTRATION"
},
{
"clue": "A state of preoccupation",
"answer": "ABSTRACTION"
}
]
